{
  "lessonTitle": "Տառային արտահայտություններ (3.11)",
  "lessonLanguage": "hy",
  "domain": "Rational Numbers",
  "difficulty": "Level 2 (Intermediate)",
  "stages": [
    {
      "stageId": "nikolski_6_ch3_11_s1",
      "type": "question_math_solution",
      "headline": "Գտե՛ք 3/4 · x արտահայտության արժեքը, եթե x = -8: Պատասխանը գրե՛ք ամբողջ թվով:",
      "headlineEnglish": "Find the value of the expression 3/4 · x if x = -8.",
      "problemText": "Evaluate 3/4 · x for x = -8.",
      "studentInput": true,
      "correctAnswer": "-6",
      "solutionSteps": "1. Տառի փոխարեն տեղադրենք տրված թիվը՝ 3/4 · (-8): 2. -8-ը և 4-ը կրճատվում են, մնում է -2: 3. 3 · (-2) = -6:",
      "solutionStepsEnglish": "1. Substitute the given value for the letter: 3/4 · (-8). 2. Simplify -8 and 4 to get -2. 3. 3 · (-2) = -6.",
      "customInstructions": "Expect exactly '-6'."
    },
    {
      "stageId": "nikolski_6_ch3_11_s2",
      "type": "question_math_solution",
      "headline": "Հաշվե՛ք a - b արտահայտության արժեքը, եթե a = -2/7 և b = 3/7: Պատասխանը գրե՛ք -a/b տեսքով:",
      "headlineEnglish": "Calculate the value of a - b if a = -2/7 and b = 3/7.",
      "problemText": "Evaluate a - b for the given signed fractions.",
      "studentInput": true,
      "correctAnswer": "-5/7",
      "solutionSteps": "1. Տեղադրենք արժեքները արտահայտության մեջ՝ -2/7 - 3/7: 2. Քանի որ հայտարարները նույնն են, կատարում ենք համարիչների հանումը՝ (-2 - 3)/7 = -5/7:",
      "solutionStepsEnglish": "1. Substitute the values into the expression: -2/7 - 3/7. 2. Since the denominators are the same, subtract the numerators: (-2 - 3)/7 = -5/7.",
      "customInstructions": "Expect exactly '-5/7'."
    },
    {
      "stageId": "nikolski_6_ch3_11_s3",
      "type": "question_math_solution",
      "headline": "Գտե՛ք 1/x արտահայտության արժեքը, եթե x = -4/5: Պատասխանը գրե՛ք կոտորակի տեսքով:",
      "headlineEnglish": "Find the value of the expression 1/x if x = -4/5.",
      "problemText": "Find the reciprocal of x = -4/5.",
      "studentInput": true,
      "correctAnswer": "-5/4",
      "solutionSteps": "1. 1/x արտահայտությունը նշանակում է 1-ը բաժանել x-ի վրա՝ 1 : (-4/5): 2. Բաժանումը փոխարինելով հակադարձով բազմապատկմամբ՝ ստանում ենք -5/4:",
      "solutionStepsEnglish": "1. The expression 1/x means 1 divided by x: 1 : (-4/5). 2. Replacing division with multiplication by the reciprocal, we get -5/4.",
      "customInstructions": "Expect exactly '-5/4'."
    },
    {
      "stageId": "nikolski_6_ch3_11_s4",
      "type": "question_math_solution",
      "headline": "Հաշվե՛ք 3a + 3b արտահայտության արժեքը, եթե հայտնի է, որ a + b = -4/3: Պատասխանը գրե՛ք ամբողջ թվով:",
      "headlineEnglish": "Calculate the value of 3a + 3b if it is known that a + b = -4/3.",
      "problemText": "Use factoring to evaluate 3a + 3b.",
      "studentInput": true,
      "correctAnswer": "-4",
      "solutionSteps": "1. Արտահայտությունից դուրս բերենք ընդհանուր արտադրիչը՝ 3a + 3b = 3(a + b): 2. Փակագծի փոխարեն տեղադրենք դրա հայտնի արժեքը՝ 3 · (-4/3): 3. 3-երը կրճատվում են, մնում է -4:",
      "solutionStepsEnglish": "1. Factor out the common multiplier: 3a + 3b = 3(a + b). 2. Substitute the known value for the parenthesis: 3 · (-4/3). 3. The 3s cancel out, leaving -4.",
      "customInstructions": "Expect exactly '-4'."
    },
    {
      "stageId": "nikolski_6_ch3_11_s5",
      "type": "question_math_solution",
      "headline": "Հաշվե՛ք (x^2 - 1) / x արտահայտության արժեքը, եթե x = -1/2: Պատասխանը գրե՛ք կոտորակի տեսքով:",
      "headlineEnglish": "Calculate the value of (x^2 - 1) / x if x = -1/2.",
      "problemText": "Evaluate the non-linear rational literal expression.",
      "studentInput": true,
      "correctAnswer": "3/2",
      "solutionSteps": "1. Հաշվենք x^2-ը՝ (-1/2)^2 = 1/4: 2. Հաշվենք համարիչը՝ 1/4 - 1 = 1/4 - 4/4 = -3/4: 3. Կատարենք բաժանումը x-ի վրա՝ (-3/4) : (-1/2) = -3/4 · (-2/1) = 6/4: 4. Կրճատելով 2-ով՝ ստանում ենք 3/2:",
      "solutionStepsEnglish": "1. Calculate x^2: (-1/2)^2 = 1/4. 2. Calculate the numerator: 1/4 - 1 = -3/4. 3. Divide by x: (-3/4) : (-1/2) = -3/4 · (-2/1) = 6/4. 4. Reduce by 2 to get 3/2.",
      "customInstructions": "Expect exactly the string '3/2'."
    }
  ]
}
